CHANGELOG.txt
LICENSE.txt
MANIFEST.in
README.txt
setup.py
dataproxy/__init__.py
dataproxy/app.py
dataproxy/dataproxy.py
dataproxy.egg-info/PKG-INFO
dataproxy.egg-info/SOURCES.txt
dataproxy.egg-info/dependency_links.txt
dataproxy.egg-info/entry_points.txt
dataproxy.egg-info/not-zip-safe
dataproxy.egg-info/requires.txt
dataproxy.egg-info/top_level.txt
dataproxy/bn/__init__.py
dataproxy/bn/relimport_test.py
dataproxy/transform/__init__.py
dataproxy/transform/base.py
dataproxy/transform/csv_transform.py
dataproxy/transform/xls_transform.py
dataproxy/xlrd/__init__.py
dataproxy/xlrd/biffh.py
dataproxy/xlrd/compdoc.py
dataproxy/xlrd/formatting.py
dataproxy/xlrd/formula.py
dataproxy/xlrd/licences.py
dataproxy/xlrd/sheet.py
dataproxy/xlrd/timemachine.py
dataproxy/xlrd/xldate.py
example/README.txt
test/.test_app.py.swp
test/test_app.py
test/test_app.pyc