Metadata-Version: 1.0
Name: dataproxy
Version: 0.1.0
Summary: A (JSONP) dataproxy
Home-page: http://ckan.org/wiki/Extensions
Author: James Gardner, Stefan Urbanek, Rufus Pollock
Author-email: ckan@okfn.org
License: GNU AGPLv3
Platform: UNKNOWN
Classifier: Development Status :: 3 - Alpha
Classifier: License :: OSI Approved :: GNU Affero General Public License v3
Classifier: Programming Language :: Python
